[{"line":1,"elements":[{"start_timestamp":"2022-07-12T22:22:54.024Z","before":[{"result":{"duration":3735640000,"status":"passed"},"match":{"location":"support.Hooks.scenarioStart()"}}],"line":8,"name":"prints all numbers from 0 up to n","description":"","id":"coding-challenges;prints-all-numbers-from-0-up-to-n;;2","after":[{"result":{"duration":133522000,"status":"passed"},"match":{"location":"support.Hooks.scenarioEnd(io.cucumber.java.Scenario)"}}],"type":"scenario","keyword":"Scenario Outline","steps":[{"result":{"duration":4950000,"status":"passed"},"line":4,"name":"I run printUpTo(n) with -1","match":{"arguments":[{"val":"-1","offset":24}],"location":"definitions.CodingChallenges.iRunPrintUpToNWith(int)"},"keyword":"When "},{"result":{"duration":3641000,"status":"passed"},"line":5,"name":"it returns \"0,-1\"","match":{"arguments":[{"val":"\"0,-1\"","offset":11}],"location":"definitions.CodingChallenges.itReturns(java.lang.String)"},"keyword":"Then "}]},{"start_timestamp":"2022-07-12T22:22:57.964Z","before":[{"result":{"duration":1384380000,"status":"passed"},"match":{"location":"support.Hooks.scenarioStart()"}}],"line":9,"name":"prints all numbers from 0 up to n","description":"","id":"coding-challenges;prints-all-numbers-from-0-up-to-n;;3","after":[{"result":{"duration":168328000,"status":"passed"},"match":{"location":"support.Hooks.scenarioEnd(io.cucumber.java.Scenario)"}}],"type":"scenario","keyword":"Scenario Outline","steps":[{"result":{"duration":3353000,"status":"passed"},"line":4,"name":"I run printUpTo(n) with 0","match":{"arguments":[{"val":"0","offset":24}],"location":"definitions.CodingChallenges.iRunPrintUpToNWith(int)"},"keyword":"When "},{"result":{"duration":2421000,"status":"passed"},"line":5,"name":"it returns \"0\"","match":{"arguments":[{"val":"\"0\"","offset":11}],"location":"definitions.CodingChallenges.itReturns(java.lang.String)"},"keyword":"Then "}]},{"start_timestamp":"2022-07-12T22:22:59.547Z","before":[{"result":{"duration":1391463000,"status":"passed"},"match":{"location":"support.Hooks.scenarioStart()"}}],"line":10,"name":"prints all numbers from 0 up to n","description":"","id":"coding-challenges;prints-all-numbers-from-0-up-to-n;;4","after":[{"result":{"duration":101964000,"status":"passed"},"match":{"location":"support.Hooks.scenarioEnd(io.cucumber.java.Scenario)"}}],"type":"scenario","keyword":"Scenario Outline","steps":[{"result":{"duration":327000,"status":"passed"},"line":4,"name":"I run printUpTo(n) with 1","match":{"arguments":[{"val":"1","offset":24}],"location":"definitions.CodingChallenges.iRunPrintUpToNWith(int)"},"keyword":"When "},{"result":{"duration":783000,"status":"passed"},"line":5,"name":"it returns \"0,1\"","match":{"arguments":[{"val":"\"0,1\"","offset":11}],"location":"definitions.CodingChallenges.itReturns(java.lang.String)"},"keyword":"Then "}]},{"start_timestamp":"2022-07-12T22:23:01.057Z","before":[{"result":{"duration":1430166000,"status":"passed"},"match":{"location":"support.Hooks.scenarioStart()"}}],"line":11,"name":"prints all numbers from 0 up to n","description":"","id":"coding-challenges;prints-all-numbers-from-0-up-to-n;;5","after":[{"result":{"duration":178944000,"status":"passed"},"match":{"location":"support.Hooks.scenarioEnd(io.cucumber.java.Scenario)"}}],"type":"scenario","keyword":"Scenario Outline","steps":[{"result":{"duration":375000,"status":"passed"},"line":4,"name":"I run printUpTo(n) with 5","match":{"arguments":[{"val":"5","offset":24}],"location":"definitions.CodingChallenges.iRunPrintUpToNWith(int)"},"keyword":"When "},{"result":{"duration":281000,"status":"passed"},"line":5,"name":"it returns \"0,1,2,3,4,5\"","match":{"arguments":[{"val":"\"0,1,2,3,4,5\"","offset":11}],"location":"definitions.CodingChallenges.itReturns(java.lang.String)"},"keyword":"Then "}]},{"start_timestamp":"2022-07-12T22:23:02.681Z","before":[{"result":{"duration":1425229000,"status":"passed"},"match":{"location":"support.Hooks.scenarioStart()"}}],"line":13,"name":"prints all integer array","description":"","id":"coding-challenges;prints-all-integer-array","after":[{"result":{"duration":109564000,"status":"passed"},"match":{"location":"support.Hooks.scenarioEnd(io.cucumber.java.Scenario)"}}],"type":"scenario","keyword":"Scenario","steps":[{"result":{"duration":543000,"status":"passed"},"line":14,"name":"I run printArrayItems(arr)","match":{"location":"definitions.CodingChallenges.iRunPrintArrayArr()"},"keyword":"When "}]},{"start_timestamp":"2022-07-12T22:23:04.248Z","before":[{"result":{"duration":1378537000,"status":"passed"},"match":{"location":"support.Hooks.scenarioStart()"}}],"line":17,"name":"prints all even numbers from integer array","description":"","id":"coding-challenges;prints-all-even-numbers-from-integer-array","after":[{"result":{"duration":128271000,"status":"passed"},"match":{"location":"support.Hooks.scenarioEnd(io.cucumber.java.Scenario)"}}],"type":"scenario","keyword":"Scenario","steps":[{"result":{"duration":492000,"status":"passed"},"line":18,"name":"I run printArrayEvenItems(arr)","match":{"location":"definitions.CodingChallenges.iRunPrintArrayEvenItemsArr()"},"keyword":"When "}]},{"start_timestamp":"2022-07-12T22:23:05.777Z","before":[{"result":{"duration":1435922000,"status":"passed"},"match":{"location":"support.Hooks.scenarioStart()"}}],"line":24,"name":"Returns false when not empty","description":"","id":"coding-challenges;returns-false-when-not-empty;;2","after":[{"result":{"duration":107740000,"status":"passed"},"match":{"location":"support.Hooks.scenarioEnd(io.cucumber.java.Scenario)"}}],"type":"scenario","keyword":"Scenario Outline","steps":[{"result":{"duration":350000,"status":"passed"},"line":21,"name":"I run isArrEmpty(array) with \"\"","match":{"arguments":[{"val":"\"\"","offset":29}],"location":"definitions.CodingChallenges.iRunIsArrEmptyArrayWithArray(java.lang.String)"},"keyword":"When "}]},{"start_timestamp":"2022-07-12T22:23:07.341Z","before":[{"result":{"duration":1428839000,"status":"passed"},"match":{"location":"support.Hooks.scenarioStart()"}}],"line":25,"name":"Returns false when not empty","description":"","id":"coding-challenges;returns-false-when-not-empty;;3","after":[{"result":{"duration":109239000,"status":"passed"},"match":{"location":"support.Hooks.scenarioEnd(io.cucumber.java.Scenario)"}}],"type":"scenario","keyword":"Scenario Outline","steps":[{"result":{"duration":691000,"status":"passed"},"line":21,"name":"I run isArrEmpty(array) with \"1\"","match":{"arguments":[{"val":"\"1\"","offset":29}],"location":"definitions.CodingChallenges.iRunIsArrEmptyArrayWithArray(java.lang.String)"},"keyword":"When "}]},{"start_timestamp":"2022-07-12T22:23:08.904Z","before":[{"result":{"duration":1476069000,"status":"passed"},"match":{"location":"support.Hooks.scenarioStart()"}}],"line":26,"name":"Returns false when not empty","description":"","id":"coding-challenges;returns-false-when-not-empty;;4","after":[{"result":{"duration":159024000,"status":"passed"},"match":{"location":"support.Hooks.scenarioEnd(io.cucumber.java.Scenario)"}}],"type":"scenario","keyword":"Scenario Outline","steps":[{"result":{"duration":393000,"status":"passed"},"line":21,"name":"I run isArrEmpty(array) with \"1,2\"","match":{"arguments":[{"val":"\"1,2\"","offset":29}],"location":"definitions.CodingChallenges.iRunIsArrEmptyArrayWithArray(java.lang.String)"},"keyword":"When "}]},{"start_timestamp":"2022-07-12T22:23:10.551Z","before":[{"result":{"duration":1425786000,"status":"passed"},"match":{"location":"support.Hooks.scenarioStart()"}}],"line":28,"name":"Checks if array contains element","description":"","id":"coding-challenges;checks-if-array-contains-element","after":[{"result":{"duration":102929000,"status":"passed"},"match":{"location":"support.Hooks.scenarioEnd(io.cucumber.java.Scenario)"}}],"type":"scenario","keyword":"Scenario","steps":[{"result":{"duration":2128000,"status":"passed"},"line":29,"name":"I run isArrContainsElem(arr)","match":{"location":"definitions.CodingChallenges.iRunIsArrContainsElemArr()"},"keyword":"When "}]}],"name":"Coding challenges","description":"","id":"coding-challenges","keyword":"Feature","uri":"file:src/test/resources/features/codingChallenges.feature","tags":[]}]